mlcast/__init__.py
mlcast/data/__init__.py
mlcast/data/zarr_datamodule.py
mlcast/data/zarr_dataset.py
mlcast/models/__init__.py
mlcast/models/base.py
mlcast/modules/__init__.py
mlcast/modules/convgru_modules.py
mlcast-0.0.1a4.dist-info/METADATA
mlcast-0.0.1a4.dist-info/WHEEL
mlcast-0.0.1a4.dist-info/licenses/LICENSE
mlcast-0.0.1a4.dist-info/RECORD
