Metadata-Version: 2.4
Name: mlcast
Version: 0.0.1a4
Summary: Machine learning weather nowcasting library
Project-URL: Documentation, https://github.com/mlcast-community/mlcast
Project-URL: Homepage, https://github.com/mlcast-community/mlcast
Project-URL: Issues, https://github.com/mlcast-community/mlcast/issues
Project-URL: Repository, https://github.com/mlcast-community/mlcast
Author-email: Gabriele Franch <franch@fbk.eu>, Leif Denby <lcd@dmi.dk>
Maintainer-email: MLCast Community <franch@fbk.eu>
License: Apache-2.0
License-File: LICENSE
Keywords: machine-learning,meteorology,nowcasting,precipitation,pytorch,radar,weather
Classifier: Development Status :: 2 - Pre-Alpha
Classifier: Intended Audience :: Science/Research
Classifier: License :: OSI Approved :: Apache Software License
Classifier: Programming Language :: Python :: 3 :: Only
Classifier: Programming Language :: Python :: 3.10
Classifier: Programming Language :: Python :: 3.11
Classifier: Programming Language :: Python :: 3.12
Classifier: Programming Language :: Python :: 3.13
Classifier: Topic :: Scientific/Engineering :: Artificial Intelligence
Classifier: Topic :: Scientific/Engineering :: Atmospheric Science
Requires-Python: >=3.10
Requires-Dist: fire>=0.7
Requires-Dist: ipykernel>=6.29.5
Requires-Dist: lightning>=2.5.2
Requires-Dist: numpy>=2.2.6
Requires-Dist: torch>=2.7.1
Requires-Dist: xarray>=2025.6.1
Requires-Dist: zarr<=3
Provides-Extra: dev
Requires-Dist: pre-commit>=3.5; extra == 'dev'
Requires-Dist: ruff>=0.8; extra == 'dev'
